LICENSE
MANIFEST.in
README.md
requirements.txt
setup.py
care_sm_toolkit.egg-info/PKG-INFO
care_sm_toolkit.egg-info/SOURCES.txt
care_sm_toolkit.egg-info/dependency_links.txt
care_sm_toolkit.egg-info/requires.txt
care_sm_toolkit.egg-info/top_level.txt
toolkit/__init__.py
toolkit/main.py
toolkit/template.py
toolkit/test/__init__.py
toolkit/test/test_pytest.py