Metadata-Version: 2.1
Name: care-sm-toolkit
Version: 1.0
Summary: A toolkit for CARE-SM data transformation.
Home-page: https://github.com/CARE-SM/CARE-SM-Toolkit
Author: Pablo Alarcón Moreno
Author-email: pabloalarconmoreno@gmail.com
License: MIT
Project-URL: Source, https://github.com/CARE-SM/CARE-SM-Toolkit
Project-URL: Bug Tracker, https://github.com/CARE-SM/CARE-SM-Toolkit/issues
Keywords: FAIR-in-a-box,Fiab,CARE-SM,Toolkit
Platform: UNKNOWN
Requires-Python: >=3.7
Provides-Extra: dev
License-File: LICENSE
